unittestreport_yami/__init__.py
unittestreport_yami/core/__init__.py
unittestreport_yami/core/dataDriver.py
unittestreport_yami/core/parameterized.py
unittestreport_yami/core/reRun.py
unittestreport_yami/core/resultPush.py
unittestreport_yami/core/screenshot.py
unittestreport_yami/core/sendEmail.py
unittestreport_yami/core/testResult.py
unittestreport_yami/core/testRunner.py
unittestreport_yami/templates/__init__.py
unittestreport_yami/templates/dingtalk.md
unittestreport_yami/templates/remote_report.md
unittestreport_yami/templates/templates.html
unittestreport_yami/templates/templates03.html
unittestreport_yami/templates/templates2.html
unittestreport_yami/templates/templates3.html
unittestreport_yami-0.1.49.dist-info/LICENSE
unittestreport_yami-0.1.49.dist-info/METADATA
unittestreport_yami-0.1.49.dist-info/WHEEL
unittestreport_yami-0.1.49.dist-info/top_level.txt
unittestreport_yami-0.1.49.dist-info/RECORD
