Metadata-Version: 2.1
Name: unittestreport_yami
Version: 0.1.49
Home-page: https://github.com/EthanLiuInyami/UnitTestReport
Author: Ethan
Author-email: ethan.liu@yamibuy.com
License: MIT
Classifier: Programming Language :: Python :: 3
Requires-Python: >=3.6
License-File: LICENSE
Requires-Dist: Jinja2==3.1.2
Requires-Dist: PyYAML==5.3.1
Requires-Dist: requests>=2.29.0
